{
    "activation text": "bdsm, bondage",
    "description": "Here is the Lora for BDSM !Below are the trigger words suggested,bondage, BDSMblindfold, shibari, ball gag, nipple clampsThe suggested weight is 0.7 - 1Hope you enjoy my work!You are welcome to browser my other works if you are interested!#New Announcement (19th April)Hello my followers. I am sorry that I bring a bad news to you today. The update frequency of Lora may be dropped dramatically or even be stopped for some reason. You can still leave your request for free (discord: qqqw123#4777) but I am not 100% sure I will make it. Thanks for your support and appreciation!#You are also welcome to leave your request for free and I will try to make it into a Lora if it is possible.If you appreciate my works, you can support me via donation on ko-fi.com/dpp12 http://ko-fi.com/dpp12",
    "sd version": "SD1",
    "modelId": 22428,
    "sha256": "F25473818766AC8489D56343B0C0CDC9CB1C2928E3D33CB152F5E09C9678E3EE"
}